{
    "hasRestrictedEnvironments": false,
    "id": 0,
    "identifier": "ba6cf5db-a05c-4090-9c1a-c2932fe9bc9e",
    "version": "1",
    "isEnabled": true,
    "isDebugMode": false,
    "name": "New Block",
    "creator": "c481700f-ff5c-4f86-9282-1425a65aae51",
    "modifiedBy": "9378d367-2470-4d0f-acb4-2303f9927e59",
    "priority": 2,
    "description": "An embedded workflow that can receive inputs and return an output.",
    "executionScope": 0,
    "environments": [
        "Default Environment"
    ],
    "categoryName": "Default",
    "categoryId": 1,
    "originalPlaybookIdentifier": "ba6cf5db-a05c-4090-9c1a-c2932fe9bc9e",
    "creationTimeUnixTimeInMs": 1782904124784,
    "modificationTimeUnixTimeInMs": 1782911677598,
    "trigger": {
        "id": 0,
        "identifier": "7d61cc5f-1dcf-4235-b674-022fbe5db22c",
        "type": 11,
        "logicalOperator": 0,
        "conditions": [],
        "reactionLogicalOperator": 1,
        "reactionConditions": [],
        "executionMode": 0
    },
    "steps": [
        {
            "parallelActions": [],
            "identifier": "260624b6-0a38-42f2-8959-32a1dace5cbe",
            "originalStepIdentifier": "260624b6-0a38-42f2-8959-32a1dace5cbe",
            "isAutomatic": true,
            "isSkippable": false,
            "instanceName": "Output_1",
            "name": "Output",
            "integration": "Flow",
            "description": "",
            "actionProvider": "Flow",
            "actionName": "OutputAction",
            "type": 6,
            "parameters": [
                {
                    "name": "NestedWorkflowOutput",
                    "value": null,
                    "type": null,
                    "isMandatory": false,
                    "defaultValue": null,
                    "id": 0,
                    "creationTimeUnixTimeInMs": 0,
                    "modificationTimeUnixTimeInMs": 0,
                    "additionalProperties": {}
                }
            ],
            "autoSkipOnFailure": false,
            "isDebugMockData": false,
            "debugData": null,
            "parentStepContainerId": null,
            "workflowIdentifier": "ba6cf5db-a05c-4090-9c1a-c2932fe9bc9e",
            "isTouchedByAi": false,
            "startLoopStepIdentifier": null,
            "logsExplorerUrl": null,
            "id": 0,
            "creationTimeUnixTimeInMs": 1782911677331,
            "modificationTimeUnixTimeInMs": 1782911677598,
            "additionalProperties": {}
        }
    ],
    "stepsRelations": [
        {
            "condition": "",
            "fromStep": "7d61cc5f-1dcf-4235-b674-022fbe5db22c",
            "toStep": "260624b6-0a38-42f2-8959-32a1dace5cbe",
            "destinationActionStatus": 0
        }
    ],
    "templateName": null,
    "playbookType": 1,
    "debugData": {
        "debugBaseAlertId": "",
        "debugAlertId": ""
    },
    "entityAccessLevel": 2,
    "defaultAccessLevel": 2,
    "permissions": [],
    "overviewTemplates": [],
    "creationSource": 1
}